agsconfig/__init__.py
agsconfig/_enum.py
agsconfig/_strutils.py
agsconfig/_version.py
agsconfig/agsconfig.py
agsconfig/model_base.py
agsconfig/editing/__init__.py
agsconfig/editing/ags_json_editor.py
agsconfig/editing/edit_prop.py
agsconfig/editing/editor_base.py
agsconfig/editing/sdd_editor.py
agsconfig/editing/serialization.py
agsconfig/services/__init__.py
agsconfig/services/cacheable_core_mixin.py
agsconfig/services/cacheable_ext_mixin.py
agsconfig/services/custom_get_capabilities_extension_mixin.py
agsconfig/services/extension_base.py
agsconfig/services/feature_server_extension.py
agsconfig/services/geocode_server.py
agsconfig/services/geodata_server.py
agsconfig/services/geoprocessing_server.py
agsconfig/services/hosted_feature_server.py
agsconfig/services/image_dimensions_mixin.py
agsconfig/services/image_server.py
agsconfig/services/interceptor_mixin.py
agsconfig/services/jpip_server_extension.py
agsconfig/services/kml_server_extension.py
agsconfig/services/map_server.py
agsconfig/services/max_record_count_mixin.py
agsconfig/services/na_server_extension.py
agsconfig/services/ogc_metadata_extension_mixin.py
agsconfig/services/output_dir_mixin.py
agsconfig/services/parcel_fabric_server_extension.py
agsconfig/services/scale_range_mixin.py
agsconfig/services/service_base.py
agsconfig/services/soi_extension_base.py
agsconfig/services/validation_server_extension.py
agsconfig/services/vector_tile_server.py
agsconfig/services/vector_tile_server_extension.py
agsconfig/services/version_management_server_extension.py
agsconfig/services/wcs_server_extension.py
agsconfig/services/wfs_server_extension.py
agsconfig/services/wms_server_extension.py
agsconfig/services/wps_server_extension.py
agsconfig-0.3.4.dist-info/LICENSE
agsconfig-0.3.4.dist-info/METADATA
agsconfig-0.3.4.dist-info/WHEEL
agsconfig-0.3.4.dist-info/top_level.txt
agsconfig-0.3.4.dist-info/RECORD
