Metadata-Version: 2.1
Name: agsconfig
Version: 0.3.4
Summary: Provides classes that can edit ArcGIS service configuration as either running services (ArcGIS Server Admin JSON format) or Service Definition Drafts.
Home-page: https://github.com/DavidWhittingham/agsconfig
Author: David Whittingham; Chris Blanchfield; Gary Bagnall
License: BSD 3-Clause
Keywords: arcgis esri
Classifier: Development Status :: 3 - Alpha
Classifier: Intended Audience :: Developers
Classifier: Natural Language :: English
Classifier: License :: OSI Approved :: BSD License
Classifier: Programming Language :: Python
Classifier: Programming Language :: Python :: 2.7
Classifier: Programming Language :: Python :: 3.6
Classifier: Programming Language :: Python :: 3.7
Classifier: Programming Language :: Python :: 3.8
Classifier: Programming Language :: Python :: 3.9
License-File: LICENSE
Requires-Dist: aenum (<4,>=3.1.5)
Requires-Dist: future (>=0.16.0)
Requires-Dist: jsonpath-ng (<2,>=1.4.3)
Requires-Dist: lxml (<5,>=4.3.2)
Requires-Dist: html2text (==2019.8.11) ; python_version < "3.0"
Requires-Dist: tzlocal (<3,>=2.0.0) ; python_version < "3.0"
Requires-Dist: html2text (>=2019.8.11) ; python_version >= "3.0"
Requires-Dist: tzlocal (<6,>=3.0.0) ; python_version >= "3.0"
